pysnmp/.DS_Store
pysnmp/__init__.py
pysnmp/cache.py
pysnmp/debug.py
pysnmp/error.py
pysnmp/nextid.py
pysnmp/carrier/__init__.py
pysnmp/carrier/base.py
pysnmp/carrier/error.py
pysnmp/carrier/sockfix.py
pysnmp/carrier/sockmsg.py
pysnmp/carrier/asyncio/__init__.py
pysnmp/carrier/asyncio/base.py
pysnmp/carrier/asyncio/dispatch.py
pysnmp/carrier/asyncio/dgram/__init__.py
pysnmp/carrier/asyncio/dgram/base.py
pysnmp/carrier/asyncio/dgram/udp.py
pysnmp/carrier/asyncio/dgram/udp6.py
pysnmp/entity/__init__.py
pysnmp/entity/config.py
pysnmp/entity/engine.py
pysnmp/entity/observer.py
pysnmp/entity/rfc3413/__init__.py
pysnmp/entity/rfc3413/cmdgen.py
pysnmp/entity/rfc3413/cmdrsp.py
pysnmp/entity/rfc3413/config.py
pysnmp/entity/rfc3413/context.py
pysnmp/entity/rfc3413/ntforg.py
pysnmp/entity/rfc3413/ntfrcv.py
pysnmp/hlapi/transport.py
pysnmp/hlapi/varbinds.py
pysnmp/hlapi/asyncio/__init__.py
pysnmp/hlapi/v1arch/__init__.py
pysnmp/hlapi/v1arch/dispatch.py
pysnmp/hlapi/v1arch/asyncio/__init__.py
pysnmp/hlapi/v1arch/asyncio/auth.py
pysnmp/hlapi/v1arch/asyncio/cmdgen.py
pysnmp/hlapi/v1arch/asyncio/dispatch.py
pysnmp/hlapi/v1arch/asyncio/ntforg.py
pysnmp/hlapi/v1arch/asyncio/slim.py
pysnmp/hlapi/v1arch/asyncio/transport.py
pysnmp/hlapi/v3arch/__init__.py
pysnmp/hlapi/v3arch/asyncio/__init__.py
pysnmp/hlapi/v3arch/asyncio/auth.py
pysnmp/hlapi/v3arch/asyncio/cmdgen.py
pysnmp/hlapi/v3arch/asyncio/context.py
pysnmp/hlapi/v3arch/asyncio/lcd.py
pysnmp/hlapi/v3arch/asyncio/ntforg.py
pysnmp/hlapi/v3arch/asyncio/transport.py
pysnmp/proto/__init__.py
pysnmp/proto/cache.py
pysnmp/proto/errind.py
pysnmp/proto/error.py
pysnmp/proto/rfc1155.py
pysnmp/proto/rfc1157.py
pysnmp/proto/rfc1901.py
pysnmp/proto/rfc1902.py
pysnmp/proto/rfc1905.py
pysnmp/proto/rfc3411.py
pysnmp/proto/rfc3412.py
pysnmp/proto/acmod/__init__.py
pysnmp/proto/acmod/rfc3415.py
pysnmp/proto/acmod/void.py
pysnmp/proto/api/__init__.py
pysnmp/proto/api/v1.py
pysnmp/proto/api/v2c.py
pysnmp/proto/api/verdec.py
pysnmp-7.1.18.dist-info/licenses/LICENSE.rst
pysnmp-7.1.18.dist-info/WHEEL
pysnmp-7.1.18.dist-info/METADATA
pysnmp-7.1.18.dist-info/RECORD
